zwergetl/__init__.py
zwergetl/components/__init__.py
zwergetl/components/base/__init__.py
zwergetl/components/base/csvreader.py
zwergetl/components/base/csvwriter.py
zwergetl/components/base/dummy.py
zwergetl/components/base/hashcalc.py
zwergetl/components/base/reformat.py
zwergetl_components_base-0.2.3.dist-info/licenses/LICENSE.txt
zwergetl_components_base-0.2.3.dist-info/METADATA
zwergetl_components_base-0.2.3.dist-info/WHEEL
zwergetl_components_base-0.2.3.dist-info/top_level.txt
zwergetl_components_base-0.2.3.dist-info/RECORD
