Metadata-Version: 2.4
Name: zwergetl-components-base
Version: 0.2.3
Summary: Basic components for ZwergETL Engine
Maintainer: dxdataworks
Requires-Python: >=3.6
License-File: LICENSE.txt
Requires-Dist: zwergetl-engine>=0.1.11
Dynamic: license-file
